LICENSE.txt
MANIFEST.in
README.md
setup.cfg
setup.py
RDfunctionLog/RDfunctionLog.pyd
RDfunctionLog/__init__.py
RDfunctionLog.egg-info/PKG-INFO
RDfunctionLog.egg-info/SOURCES.txt
RDfunctionLog.egg-info/dependency_links.txt
RDfunctionLog.egg-info/top_level.txt
RDfunctionLog/Ui/__init__.py
RDfunctionLog/Ui/functionLogUi.pyd